[
  {
    "ContainingType": "ExampleWebAPI.Controllers.Auth.AuthController",
    "Method": "Login",
    "RelativePath": "api/Auth/Login",
    "HttpMethod": "POST",
    "IsController": true,
    "Order": 0,
    "Parameters": [
      {
        "Name": "login",
        "Type": "WebApiAdvanceExample.Entities.DTOs.AutDTOs.LoginDto",
        "IsRequired": true
      }
    ],
    "ReturnTypes": []
  },
  {
    "ContainingType": "ExampleWebAPI.Controllers.Auth.AuthController",
    "Method": "RegisterUser",
    "RelativePath": "api/Auth/RegisterUser/User Register",
    "HttpMethod": "POST",
    "IsController": true,
    "Order": 0,
    "Parameters": [
      {
        "Name": "register",
        "Type": "WebApiAdvanceExample.Entities.DTOs.AutDTOs.RegisterDto",
        "IsRequired": true
      }
    ],
    "ReturnTypes": []
  },
  {
    "ContainingType": "ExampleWebAPI.Controllers.CategoriesController",
    "Method": "AddCategory",
    "RelativePath": "api/Categories/AddCategory",
    "HttpMethod": "POST",
    "IsController": true,
    "Order": 0,
    "Parameters": [
      {
        "Name": "dto",
        "Type": "WebApiAdvanceExample.Entities.DTOs.CategoryDTOs.CreateCategoryDto",
        "IsRequired": true
      }
    ],
    "ReturnTypes": []
  },
  {
    "ContainingType": "ExampleWebAPI.Controllers.CategoriesController",
    "Method": "DeleteCategory",
    "RelativePath": "api/Categories/DeleteCategory/{id}",
    "HttpMethod": "DELETE",
    "IsController": true,
    "Order": 0,
    "Parameters": [
      {
        "Name": "id",
        "Type": "System.Guid",
        "IsRequired": true
      }
    ],
    "ReturnTypes": []
  },
  {
    "ContainingType": "ExampleWebAPI.Controllers.CategoriesController",
    "Method": "GetAllCategories",
    "RelativePath": "api/Categories/GetAllCategories",
    "HttpMethod": "GET",
    "IsController": true,
    "Order": 0,
    "Parameters": [],
    "ReturnTypes": []
  },
  {
    "ContainingType": "ExampleWebAPI.Controllers.CategoriesController",
    "Method": "GetCategoryById",
    "RelativePath": "api/Categories/GetCategoryById/{id}",
    "HttpMethod": "GET",
    "IsController": true,
    "Order": 0,
    "Parameters": [
      {
        "Name": "id",
        "Type": "System.Guid",
        "IsRequired": true
      }
    ],
    "ReturnTypes": []
  },
  {
    "ContainingType": "NtierArchitecture.WebAPI.Controllers.MailController",
    "Method": "SendEmail",
    "RelativePath": "api/Mail/send-email",
    "HttpMethod": "POST",
    "IsController": true,
    "Order": 0,
    "Parameters": [
      {
        "Name": "request",
        "Type": "NtierArchitecture.Entities.DTOs.ContactDTOs.EmailRequestDto",
        "IsRequired": true
      }
    ],
    "ReturnTypes": []
  },
  {
    "ContainingType": "ExampleWebAPI.Controllers.ProductsController",
    "Method": "AddProduct",
    "RelativePath": "api/Products/AddProduct",
    "HttpMethod": "POST",
    "IsController": true,
    "Order": 0,
    "Parameters": [
      {
        "Name": "CategoryId",
        "Type": "System.Guid",
        "IsRequired": false
      },
      {
        "Name": "Name",
        "Type": "System.String",
        "IsRequired": false
      },
      {
        "Name": "Description",
        "Type": "System.String",
        "IsRequired": false
      },
      {
        "Name": "Price",
        "Type": "System.Decimal",
        "IsRequired": false
      },
      {
        "Name": "DiscountPrice",
        "Type": "System.Nullable\u00601[[System.Decimal, System.Private.CoreLib, Version=10.0.0.0, Culture=neutral, PublicKeyToken=7cec85d7bea7798e]]",
        "IsRequired": false
      },
      {
        "Name": "Status",
        "Type": "System.Nullable\u00601[[WebApiAdvanceExample.Entities.Enums.ProductStatus, NtierArchitecture.Entities, Version=1.0.0.0, Culture=neutral, PublicKeyToken=null]]",
        "IsRequired": false
      },
      {
        "Name": "ImageUrl",
        "Type": "Microsoft.AspNetCore.Http.IFormFile",
        "IsRequired": false
      }
    ],
    "ReturnTypes": []
  },
  {
    "ContainingType": "ExampleWebAPI.Controllers.ProductsController",
    "Method": "DeleteProduct",
    "RelativePath": "api/Products/DeleteProduct/{id}",
    "HttpMethod": "DELETE",
    "IsController": true,
    "Order": 0,
    "Parameters": [
      {
        "Name": "id",
        "Type": "System.Guid",
        "IsRequired": false
      },
      {
        "Name": "id",
        "Type": "",
        "IsRequired": true
      }
    ],
    "ReturnTypes": []
  },
  {
    "ContainingType": "ExampleWebAPI.Controllers.ProductsController",
    "Method": "GetAllProducts",
    "RelativePath": "api/Products/GetAllProducts",
    "HttpMethod": "GET",
    "IsController": true,
    "Order": 0,
    "Parameters": [],
    "ReturnTypes": []
  },
  {
    "ContainingType": "ExampleWebAPI.Controllers.ProductsController",
    "Method": "GetProductById",
    "RelativePath": "api/Products/GetProductById/{id}",
    "HttpMethod": "GET",
    "IsController": true,
    "Order": 0,
    "Parameters": [
      {
        "Name": "id",
        "Type": "System.Guid",
        "IsRequired": true
      }
    ],
    "ReturnTypes": []
  }
]